lib_mail/__init__.py
lib_mail/mailbox.py
lib_mail-0.2.6.dist-info/METADATA
lib_mail-0.2.6.dist-info/WHEEL
lib_mail-0.2.6.dist-info/RECORD
