Metadata-Version: 2.3
Name: lib-mail
Version: 0.2.6
Summary: 
Author: Nathan Blum
Author-email: n.blum@student.tudelft.nl
Requires-Python: >=3.10
Classifier: Programming Language :: Python :: 3
Classifier: Programming Language :: Python :: 3.10
Classifier: Programming Language :: Python :: 3.11
Classifier: Programming Language :: Python :: 3.12
Classifier: Programming Language :: Python :: 3.13
Requires-Dist: beautifulsoup4 (>=4.13.4,<5.0.0)
Requires-Dist: chardet (>=5.2.0,<6.0.0)
Requires-Dist: redis (>=6.2.0,<7.0.0)
